MANIFEST.in
README.md
VERSION.txt
setup.py
django_simple_static_file_storage.egg-info/PKG-INFO
django_simple_static_file_storage.egg-info/SOURCES.txt
django_simple_static_file_storage.egg-info/dependency_links.txt
django_simple_static_file_storage.egg-info/not-zip-safe
django_simple_static_file_storage.egg-info/top_level.txt
simple_static_file_storage/__init__.py