Metadata-Version: 1.0
Name: django-simple-static-file-storage
Version: 1.0.2
Summary: Simple static file storage for user uploads.
Home-page: https://github.com/matix-io/django-simple-static-file-storage
Author: Connor Bode
Author-email: connor@matix.io
License: MIT
Platform: UNKNOWN
